edc_selenium/__init__.py
edc_selenium/settings.py
edc_selenium/tests.py
edc_selenium/urls.py
edc_selenium/wsgi.py
edc_selenium/mixins/__init__.py
edc_selenium/mixins/selenium_login_mixin.py
edc_selenium/mixins/selenium_model_form_mixin.py
edc_selenium/mixins/selenium_utils_mixin.py
edc_selenium-0.1.3.dist-info/LICENSE
edc_selenium-0.1.3.dist-info/METADATA
edc_selenium-0.1.3.dist-info/WHEEL
edc_selenium-0.1.3.dist-info/top_level.txt
edc_selenium-0.1.3.dist-info/RECORD
